gogo_cli/__init__.py
gogo_cli/__main__.py
gogo_cli/core/__gogo_cli__.py
gogo_cli/core/__init__.py
gogo_cli/core/__version__.py
gogo_cli/core/utils/__cast__.py
gogo_cli/core/utils/__downloader__.py
gogo_cli/core/utils/__init__.py
gogo_cli/core/utils/__menu__.py
gogo_cli/core/utils/__player__.py
gogo_cli-0.1.3.dist-info/LICENSE
gogo_cli-0.1.3.dist-info/METADATA
gogo_cli-0.1.3.dist-info/WHEEL
gogo_cli-0.1.3.dist-info/entry_points.txt
gogo_cli-0.1.3.dist-info/RECORD
