Metadata-Version: 2.1
Name: gogo-cli
Version: 0.1.3
Summary: A cli tool to browse and play anime.
License: GPLv3
Author: DemonKingSwarn
Author-email: rockingswarn@gmail.com
Requires-Python: >=3.10,<4.0
Classifier: License :: Other/Proprietary License
Classifier: Programming Language :: Python :: 3
Classifier: Programming Language :: Python :: 3.10
Classifier: Programming Language :: Python :: 3.11
Requires-Dist: catt (==0.12.11)
Requires-Dist: httpx (==0.23.0)
